ptnad/__init__.py
ptnad/auth.py
ptnad/client.py
ptnad/exceptions.py
ptnad/py.typed
ptnad/api/__init__.py
ptnad/api/bql.py
ptnad/api/monitoring.py
ptnad/api/replists.py
ptnad/api/signatures.py
ptnad_client_test-0.1.132.dist-info/METADATA
ptnad_client_test-0.1.132.dist-info/WHEEL
ptnad_client_test-0.1.132.dist-info/licenses/LICENSE
ptnad_client_test-0.1.132.dist-info/RECORD
