Metadata-Version: 2.4
Name: ptnad-client-test
Version: 0.1.132
Summary: Python library for interacting with the PT NAD API
Project-URL: Homepage, https://github.com/Reversenant/ptnad-client-test
Project-URL: Documentation, https://reversenant.github.io/ptnad-client/
Project-URL: Repository, https://github.com/Reversenant/ptnad-client-test
Project-URL: Issues, https://github.com/Reversenant/ptnad-client-test/issues
Author: Andrey Tyulenev
License-Expression: MIT
License-File: LICENSE
Classifier: License :: OSI Approved :: MIT License
Classifier: Programming Language :: Python :: 3
Requires-Python: >=3.12
Requires-Dist: mkdocs
Requires-Dist: mkdocs-material
Requires-Dist: mkdocs-static-i18n
Requires-Dist: mkdocstrings-python
Requires-Dist: requests>=2.32.3
Requires-Dist: termynal
